ywdblogmath/__init__.py
ywdblogmath/add.py
ywdblogmath/division.py
ywdblogmath/multiply.py
ywdblogmath/subtract.py
ywdblogmath/adv/__init__.py
ywdblogmath/adv/sqrt.py
ywdblogmath-0.4.dist-info/DESCRIPTION.rst
ywdblogmath-0.4.dist-info/METADATA
ywdblogmath-0.4.dist-info/RECORD
ywdblogmath-0.4.dist-info/WHEEL
ywdblogmath-0.4.dist-info/metadata.json
ywdblogmath-0.4.dist-info/top_level.txt
