Metadata-Version: 2.0
Name: ywdblogmath
Version: 0.4
Summary: A silly ywdblogmath package
Home-page: http://www.yudadan.com/
Author: ywdblog
Author-email: ywdblog@gmail.com
License: UNKNOWN
Platform: UNKNOWN
